wgs2json/__init__.py
wgs2json/__main__.py
wgs2json/core.py
wgs2json/models.py
wgs2json/utils.py
wgs2json-0.0.1.dist-info/METADATA
wgs2json-0.0.1.dist-info/WHEEL
wgs2json-0.0.1.dist-info/top_level.txt
wgs2json-0.0.1.dist-info/RECORD
